src/__init__.py
src/embeddings/__init__.py
src/embeddings/embedding_factory.py
src/embeddings/embedding_utils.py
src/models/__init__.py
src/models/attention_factory.py
src/models/base_model.py
src/models/fttransformer.py
src/models/mlp.py
src/models/model_utils.py
src/training/__init__.py
src/training/configs.py
src/training/dataset.py
src/training/encoder.py
src/training/initializers.py
src/training/losses.py
src/training/model_builder.py
src/training/trainer.py
src/training/training_utils.py
advanced_tabular_nn_models_pt-0.2.0.dist-info/LICENSE
advanced_tabular_nn_models_pt-0.2.0.dist-info/METADATA
advanced_tabular_nn_models_pt-0.2.0.dist-info/WHEEL
advanced_tabular_nn_models_pt-0.2.0.dist-info/top_level.txt
advanced_tabular_nn_models_pt-0.2.0.dist-info/RECORD
